README.md
setup.cfg
setup.py
noty/__init__.py
noty/main.py
noty.egg-info/PKG-INFO
noty.egg-info/SOURCES.txt
noty.egg-info/dependency_links.txt
noty.egg-info/entry_points.txt
noty.egg-info/top_level.txt