Metadata-Version: 1.0
Name: noty
Version: 0.11.0
Summary: Creating sticky notes has never been easier.
Home-page: https://github.com/GrgBls/noty
Author: GrgBls
Author-email: grgbls647@gmail.com
License: MIT
Platform: UNKNOWN
